imgtools/__init__.py
imgtools/autopipeline.py
imgtools/autopipeline_utils.py
imgtools/exceptions.py
imgtools/nnunet_pipeline.py
imgtools/py.typed
imgtools/cli/__init__.py
imgtools/cli/__main__.py
imgtools/cli/autopipeline.py
imgtools/cli/dicomfind.py
imgtools/cli/dicomshow.py
imgtools/cli/dicomsort.py
imgtools/cli/index.py
imgtools/cli/interlacer.py
imgtools/cli/nnunet_pipeline.py
imgtools/cli/sectioned_group.py
imgtools/cli/testdatasets.py
imgtools/coretypes/Mask_VectorMask.md
imgtools/coretypes/__init__.py
imgtools/coretypes/base_masks.py
imgtools/coretypes/base_medimage.py
imgtools/coretypes/box.py
imgtools/coretypes/image-1.png
imgtools/coretypes/image.png
imgtools/coretypes/imagetypes/__init__.py
imgtools/coretypes/imagetypes/dose.py
imgtools/coretypes/imagetypes/pet.py
imgtools/coretypes/imagetypes/scan.py
imgtools/coretypes/masktypes/README.md
imgtools/coretypes/masktypes/__init__.py
imgtools/coretypes/masktypes/__main__.py
imgtools/coretypes/masktypes/roi_matching.py
imgtools/coretypes/masktypes/seg.py
imgtools/coretypes/masktypes/structureset.py
imgtools/coretypes/spatial_types/README.md
imgtools/coretypes/spatial_types/__init__.py
imgtools/coretypes/spatial_types/coord_types.py
imgtools/coretypes/spatial_types/direction.py
imgtools/coretypes/spatial_types/image_geometry.py
imgtools/datasets/__init__.py
imgtools/datasets/examples.py
imgtools/datasets/github_datasets.py
imgtools/datasets/sample_images.py
imgtools/datasets/data/merged_duck_with_star.nii.gz
imgtools/datasets/data/star_mask.nii.gz
imgtools/dicom/__init__.py
imgtools/dicom/dicom_find.py
imgtools/dicom/dicom_reader.py
imgtools/dicom/interlacer.py
imgtools/dicom/read_tags.py
imgtools/dicom/utils.py
imgtools/dicom/crawl/__init__.py
imgtools/dicom/crawl/crawler.py
imgtools/dicom/crawl/parse_dicoms.py
imgtools/dicom/dicom_metadata/__init__.py
imgtools/dicom/dicom_metadata/__main__.py
imgtools/dicom/dicom_metadata/extractor_base.py
imgtools/dicom/dicom_metadata/extractors.py
med_imagetools-2.13.1.dist-info/METADATA
med_imagetools-2.13.1.dist-info/WHEEL
med_imagetools-2.13.1.dist-info/entry_points.txt
med_imagetools-2.13.1.dist-info/licenses/LICENSE
med_imagetools-2.13.1.dist-info/RECORD
