Metadata-Version: 2.4
Name: med-imagetools
Version: 2.13.1
Summary: Med-Imagetools: Transparent and Reproducible Medical Image Processing Pipelines in Python
Project-URL: homepage, https://github.com/bhklab/med-imagetools
Project-URL: documentation, https://bhklab.github.io/med-imagetools/
Project-URL: issues, https://github.com/bhklab/med-imagetools/issues
Author: Sejin Kim, Michal Kazmierski, Kevin Qu, Vishwesh Ramanathan, Jermiah Joseph
Author-email: Benjamin Haibe-Kains <benjamin.haibe.kains@utoronto.ca>
Maintainer-email: Benjamin Haibe-Kains <benjamin.haibe.kains@utoronto.ca>
License-Expression: MIT
License-File: LICENSE
Classifier: Development Status :: 4 - Beta
Classifier: Intended Audience :: Developers
Classifier: Intended Audience :: Healthcare Industry
Classifier: Intended Audience :: Science/Research
Classifier: License :: OSI Approved :: MIT License
Classifier: Natural Language :: English
Classifier: Operating System :: MacOS
Classifier: Operating System :: OS Independent
Classifier: Operating System :: POSIX :: Linux
Classifier: Programming Language :: Python :: 3.10
Classifier: Programming Language :: Python :: 3.11
Classifier: Programming Language :: Python :: 3.12
Classifier: Programming Language :: Python :: 3.13
Classifier: Topic :: Scientific/Engineering :: Image Processing
Classifier: Topic :: Scientific/Engineering :: Medical Science Apps.
Classifier: Topic :: Scientific/Engineering :: Visualization
Classifier: Topic :: Software Development :: Libraries :: Python Modules
Classifier: Topic :: Utilities
Classifier: Typing :: Typed
Requires-Python: <4,>=3.10
Requires-Dist: click<9,>=8.1
Requires-Dist: dill<1,>=0.3.8
Requires-Dist: dpath>=2.2.0
Requires-Dist: fasteners==0.19
Requires-Dist: highdicom
Requires-Dist: joblib<2,>=1.4.2
Requires-Dist: matplotlib<4,>=3.8.4
Requires-Dist: numpy<3
Requires-Dist: pandas<3
Requires-Dist: pydantic-settings<3,>=2.8.1
Requires-Dist: pydicom>=2.4.4
Requires-Dist: pyyaml<7,>=6.0
Requires-Dist: rich>=13.9.4
Requires-Dist: scikit-image<1,>=0.23.2
Requires-Dist: simpleitk<3,>=2.4.0
Requires-Dist: structlog<26,>=25.0
Requires-Dist: tqdm<5,>=4.66.4
Provides-Extra: all
Requires-Dist: aiohttp>=3.8.1; extra == 'all'
Requires-Dist: pygithub>=2.5.0; extra == 'all'
Requires-Dist: pyvis<0.4,>=0.3.2; extra == 'all'
Provides-Extra: datasets
Requires-Dist: aiohttp>=3.8.1; extra == 'datasets'
Requires-Dist: pygithub>=2.5.0; extra == 'datasets'
Provides-Extra: pyvis
Requires-Dist: pyvis<0.4,>=0.3.2; extra == 'pyvis'
